chatimusmaximus/__init__.py
chatimusmaximus/__main__.py
chatimusmaximus/default_settings.yml
chatimusmaximus/messaging.py
chatimusmaximus/scratch.py
chatimusmaximus/gui/__init__.py
chatimusmaximus/gui/central_widget.py
chatimusmaximus/gui/command_line.py
chatimusmaximus/gui/main_window.py
chatimusmaximus/gui/menu_bar.py
chatimusmaximus/gui/message_area.py
chatimusmaximus/gui/status_bar.py
chatimusmaximus/gui/models/__init__.py
chatimusmaximus/gui/models/settings_model.py
chatimusmaximus/gui/resources/click.wav
chatimusmaximus/gui/resources/buttons/green_button.png
chatimusmaximus/gui/resources/buttons/red_button.png
chatimusmaximus/gui/resources/icons/command_line.png
chatimusmaximus/gui/resources/icons/livecoding.png
chatimusmaximus/gui/resources/icons/twitch.png
chatimusmaximus/gui/resources/icons/vex.png
chatimusmaximus/gui/resources/icons/watchpeoplecode.png
chatimusmaximus/gui/resources/icons/youtube.png
chatimusmaximus-0.5.1.dist-info/DESCRIPTION.rst
chatimusmaximus-0.5.1.dist-info/METADATA
chatimusmaximus-0.5.1.dist-info/RECORD
chatimusmaximus-0.5.1.dist-info/WHEEL
chatimusmaximus-0.5.1.dist-info/entry_points.txt
chatimusmaximus-0.5.1.dist-info/metadata.json
chatimusmaximus-0.5.1.dist-info/top_level.txt
