Metadata-Version: 2.0
Name: chatimusmaximus
Version: 0.5.1
Summary: Chat GUI for youtube, twitch, livecoding, and WatchPeopleCode chats
Home-page: https://github.com/benhoff/chatimusmaximus
Author: Ben Hoff
Author-email: beohoff@gmail.com
License: GPL3
Platform: UNKNOWN
Classifier: Development Status :: 1 - Planning
Classifier: Intended Audience :: Developers
Classifier: License :: OSI Approved :: GNU General Public License v3 (GPLv3)
Classifier: Programming Language :: Python :: 3
Classifier: Programming Language :: Python :: 3.5
Classifier: Topic :: Utilities
Classifier: Operating System :: OS Independent
Requires-Dist: PyQt5
Requires-Dist: PyYAML
Requires-Dist: Quamash
Requires-Dist: pluginmanager
Requires-Dist: pyzmq
Requires-Dist: vexbot
Requires-Dist: vexmessage
Provides-Extra: dev
Requires-Dist: flake8; extra == 'dev'
